pyquran/README.md
pyquran/__init__.py
pyquran/QuranCorpus/quran-uthmani-md5.txt
pyquran/QuranCorpus/quran-uthmani.xml
pyquran/core/__init__.py
pyquran/core/pyquran.py
pyquran/documentation/__init__.py
pyquran/documentation/auto_gen_docs.py
pyquran/tools/AI.py
pyquran/tools/__init__.py
pyquran/tools/arabic.py
pyquran/tools/buckwalter.py
pyquran/tools/error.py
pyquran/tools/filtering.py
pyquran/tools/quran.py
pyquran/tools/searchHelper.py
pyquran/tools/shapeHelper.py
pyquran-1.0.1.dist-info/METADATA
pyquran-1.0.1.dist-info/RECORD
pyquran-1.0.1.dist-info/WHEEL
pyquran-1.0.1.dist-info/top_level.txt
