Metadata-Version: 2.1
Name: pyquran
Version: 1.0.1
Summary: PyQuran: The Python package for Quranic Analysis
Home-page: https://github.com/hci-lab/PyQuran
Author: Waleed A. Yousef and Taha M. Madbouly and Omar M. Ibrahime and Ali H. El-Kassas and Ali O. Hassan and Abdallah R. Albohy
Author-email: tahamagdy@fci.helwan.edu.eg
License: UNKNOWN
Platform: UNKNOWN
